cwmon_mysql/__init__.py
cwmon_mysql/__main__.py
cwmon_mysql/cli.py
cwmon_mysql/metrics.py
cwmon_mysql-0.5.0.dist-info/DESCRIPTION.rst
cwmon_mysql-0.5.0.dist-info/METADATA
cwmon_mysql-0.5.0.dist-info/RECORD
cwmon_mysql-0.5.0.dist-info/WHEEL
cwmon_mysql-0.5.0.dist-info/entry_points.txt
cwmon_mysql-0.5.0.dist-info/metadata.json
cwmon_mysql-0.5.0.dist-info/top_level.txt
