Metadata-Version: 2.0
Name: cwmon-mysql
Version: 0.5.0
Summary: A cwmon plugin for monitoring MySQL.
Home-page: https://github.com/RescueTime/cwmon-mysql
Author: Hank Gay
Author-email: hank@rescuetime.com
License: BSD
Keywords: monitoring,AWS,CloudWatch,MySQL
Platform: UNKNOWN
Classifier: Development Status :: 3 - Alpha
Classifier: Intended Audience :: System Administrators
Classifier: License :: OSI Approved :: BSD License
Classifier: Operating System :: Unix
Classifier: Operating System :: POSIX
Classifier: Operating System :: Microsoft :: Windows
Classifier: Programming Language :: Python
Classifier: Programming Language :: Python :: 3
Classifier: Programming Language :: Python :: 3.3
Classifier: Programming Language :: Python :: 3.4
Classifier: Programming Language :: Python :: 3.5
Classifier: Programming Language :: Python :: Implementation :: CPython
Classifier: Topic :: Utilities
Requires-Dist: click
Requires-Dist: cwmon (>=0.5.0)
Requires-Dist: pymysql
Provides-Extra: dev
Requires-Dist: tox; extra == 'dev'
Requires-Dist: detox; extra == 'dev'
Requires-Dist: twine; extra == 'dev'
Requires-Dist: wheel; extra == 'dev'
Requires-Dist: bumpversion; extra == 'dev'
Requires-Dist: gitchangelog; extra == 'dev'
